TSolLum/__init__.py
TSolLum/astm_g_173
TSolLum/d65
TSolLum/exceptions.py
TSolLum/read_spectrum.py
TSolLum/spectra.py
TSolLum/transmittance_calculator.py
TSolLum/v-lambda
TSolLum-23.7.dist-info/METADATA
TSolLum-23.7.dist-info/WHEEL
TSolLum-23.7.dist-info/top_level.txt
TSolLum-23.7.dist-info/RECORD
