Metadata-Version: 2.1
Name: TSolLum
Version: 23.7
Summary: TSolLum is a Python package designed to analyze the optical properties of a smart window coating material called vanadium dioxide.
Home-page: https://github.com/JoHpt/TSolLum
Author: JoHpt
Classifier: Programming Language :: Python :: 3
Classifier: License :: OSI Approved :: MIT License
Classifier: Operating System :: OS Independent
Requires-Python: >=3.8
Requires-Dist: numpy
Requires-Dist: scipy
Requires-Dist: pandas
Requires-Dist: matplotlib
